src/__init__.py
src/helpers.py
src/main.py
src/plugins/json_schema/asn.py
src/plugins/json_schema/ip.py
src/plugins/json_schema/validator.py
src/plugins/json_schema/vlan.py
net_schema-1.0.0.dist-info/METADATA
net_schema-1.0.0.dist-info/WHEEL
net_schema-1.0.0.dist-info/entry_points.txt
net_schema-1.0.0.dist-info/licenses/LICENSE
net_schema-1.0.0.dist-info/RECORD
