Metadata-Version: 2.4
Name: net-schema
Version: 1.0.0
Summary: Net Schema is a library that allows you to validate the schema of your YAML documents. For example your Ansible host vars or group vars.
Project-URL: Homepage, https://github.com/packetcoders/net-schema
Project-URL: Documentation, https://github.com/packetcoders/net-schema
Author-email: PacketCoders <contact@packetcoders.io>
License-File: LICENSE
Keywords: jsonschema,python
Classifier: Intended Audience :: Developers
Classifier: Programming Language :: Python :: 3.11
Requires-Python: ~=3.11
Requires-Dist: isort<7,>=6.0.1
Requires-Dist: jsonschema<5,>=4.19.0
Requires-Dist: jupyter-client<9,>=8.6.3
Requires-Dist: pyyaml<7,>=6.0.1
Requires-Dist: referencing<0.31,>=0.30.2
Requires-Dist: rich<14,>=13.9.4
Requires-Dist: typer<0.10,>=0.9.4
Requires-Dist: types-pyyaml==6.0.12
